nlp_toolkit_services_py_client/__init__.py
nlp_toolkit_services_py_client/dependency_pb2.py
nlp_toolkit_services_py_client/dependency_pb2.pyi
nlp_toolkit_services_py_client/dependency_pb2_grpc.py
nlp_toolkit_services_py_client/ner_pb2.py
nlp_toolkit_services_py_client/ner_pb2.pyi
nlp_toolkit_services_py_client/ner_pb2_grpc.py
nlp_toolkit_services_py_client/text_classification_pb2.py
nlp_toolkit_services_py_client/text_classification_pb2.pyi
nlp_toolkit_services_py_client/text_classification_pb2_grpc.py
nlp_toolkit_services_py_client/word_segment_pb2.py
nlp_toolkit_services_py_client/word_segment_pb2.pyi
nlp_toolkit_services_py_client/word_segment_pb2_grpc.py
nlp_toolkit_services-0.1.9.dist-info/METADATA
nlp_toolkit_services-0.1.9.dist-info/WHEEL
nlp_toolkit_services-0.1.9.dist-info/top_level.txt
nlp_toolkit_services-0.1.9.dist-info/RECORD
