Metadata-Version: 2.4
Name: nlp-toolkit-services
Version: 0.1.9
Summary: Python gRPC client stubs for the nlp services.
Project-URL: Homepage, https://github.com/citadel-reader/nlp-toolkit-services
Project-URL: Repository, https://github.com/citadel-reader/nlp-toolkit-services
Requires-Python: >=3.9
Requires-Dist: grpcio>=1.68.1
Requires-Dist: protobuf>=5
